pytorch_lightning_helper/__init__.py
pytorch_lightning_helper/model.py
pytorch_lightning_helper-0.0.6.dist-info/METADATA
pytorch_lightning_helper-0.0.6.dist-info/WHEEL
pytorch_lightning_helper-0.0.6.dist-info/top_level.txt
pytorch_lightning_helper-0.0.6.dist-info/RECORD
