Metadata-Version: 2.1
Name: pytorch-lightning-helper
Version: 0.0.6
Summary: Pytorch lightning helper
Home-page: https://github.com/automatethem/pytorch-lightning-helper
Author: Sang Ki Kwon
Author-email: automatethem@gmail.com
License: MIT
Platform: UNKNOWN
